avro_json_serializer/__init__.py
avro_json_serializer-1.0.3.dist-info/LICENSE.TXT
avro_json_serializer-1.0.3.dist-info/METADATA
avro_json_serializer-1.0.3.dist-info/WHEEL
avro_json_serializer-1.0.3.dist-info/top_level.txt
avro_json_serializer-1.0.3.dist-info/RECORD
