Metadata-Version: 2.1
Name: avro-json-serializer
Version: 1.0.3
Summary: Avro Json Serializer
Home-page: UNKNOWN
Author: Roman Inozemtsev
Author-email: rinozemtsev@linkedin.com
License: Apache 2.0
Platform: UNKNOWN
Requires-Dist: six
